fixturefilehandler/__init__.py
fixturefilehandler/exceptions.py
fixturefilehandler/factories.py
fixturefilehandler/file_paths.py
fixturefilehandler/fixture_file_handler.py
fixturefilehandler/py.typed
tests/__init__.py
tests/conftest.py
tests/test___init__.py
tests/test_factories.py
tests/test_file_paths.py
tests/testlibraries/__init__.py
tests/testlibraries/fixturefilehandlerfortest/__init__.py
tests/testlibraries/fixturefilehandlerfortest/file_paths_for_test.py
tests/testlibraries/fixturefilehandlerfortest/fixture_file_handlers_for_test.py
tests/testlibraries/parametrizer/__init__.py
tests/testlibraries/parametrizer/action_executors.py
tests/testlibraries/parametrizer/checkers.py
tests/testlibraries/parametrizer/file_path_state_handlers.py
tests/testlibraries/parametrizer/file_path_with_resource_factories.py
tests/testlibraries/parametrizer/file_states.py
tests/testscenarios/__init__.py
tests/testscenarios/test_config_handler_pytest.py
tests/testscenarios/test_config_handler_unittest.py
yourproduct/__init__.py
yourproduct/pytest_context_advanced.py
yourproduct/pytest_context_basic.py
yourproduct/test.txt
yourproduct/unittest_context_advanced.py
yourproduct/unittest_context_basic.py
fixturefilehandler-1.4.0.dist-info/LICENSE
fixturefilehandler-1.4.0.dist-info/METADATA
fixturefilehandler-1.4.0.dist-info/WHEEL
fixturefilehandler-1.4.0.dist-info/top_level.txt
fixturefilehandler-1.4.0.dist-info/RECORD
