Metadata-Version: 2.1
Name: fixturefilehandler
Version: 1.4.0
Summary: This project helps you to vacate specific file path or deploy resource file into specific file path when unit testing.
Home-page: https://github.com/yukihiko-shinoda/fixture-file-handler
Author: Yukihiko Shinoda
Author-email: yuk.hik.future@gmail.com
License: UNKNOWN
Keywords: fixture file vacate deploy unittest pytest testing
Platform: UNKNOWN
Classifier: Development Status :: 5 - Production/Stable
Classifier: Intended Audience :: Developers
Classifier: License :: OSI Approved :: MIT License
Classifier: Natural Language :: English
Classifier: Operating System :: OS Independent
Classifier: Programming Language :: Python
Classifier: Programming Language :: Python :: 3
Classifier: Programming Language :: Python :: 3.7
Classifier: Programming Language :: Python :: 3.8
Classifier: Topic :: Software Development
Classifier: Topic :: Software Development :: Testing
Classifier: Topic :: Software Development :: Testing :: Unit
Classifier: Topic :: System
Classifier: Topic :: System :: Filesystems
Classifier: Typing :: Typed
Requires-Python: >=3.7
